mongoengine_arrow/__init__.py
mongoengine_arrow-0.1.3.dist-info/LICENSE
mongoengine_arrow-0.1.3.dist-info/WHEEL
mongoengine_arrow-0.1.3.dist-info/METADATA
mongoengine_arrow-0.1.3.dist-info/RECORD
