Metadata-Version: 2.1
Name: mongoengine-arrow
Version: 0.1.3
Summary: Arrow datetime support for MongoEngine
Home-page: https://github.com/b10011/mongoengine-arrow
Keywords: arrow,mongoengine,database
Author: Niko Järvinen
Author-email: nbjarvinen@gmail.com
Requires-Python: >=3.6,<4.0
Classifier: Development Status :: 4 - Beta
Classifier: Intended Audience :: Developers
Classifier: License :: OSI Approved :: MIT License
Classifier: Programming Language :: Python :: 3
Classifier: Programming Language :: Python :: 3.6
Classifier: Programming Language :: Python :: 3.7
Classifier: Programming Language :: Python :: 3.8
Classifier: Programming Language :: Python :: 3.9
Classifier: Topic :: Software Development :: Libraries
Classifier: Topic :: Utilities
Requires-Dist: arrow (>=0.17.0,<0.18.0)
Requires-Dist: mongoengine (>=0.22.1,<0.23.0)
Project-URL: Documentation, https://github.com/b10011/mongoengine-arrow
Project-URL: Repository, https://github.com/b10011/mongoengine-arrow
